<?xml version="1.0" encoding="UTF-8" standalone="yes"?>
<idPkg:Spread xmlns:idPkg="http://ns.adobe.com/AdobeInDesign/idml/1.0/packaging" DOMVersion="16.2">
	<Spread Self="uc8" PageTransitionType="None" PageTransitionDirection="NotApplicable" PageTransitionDuration="Medium" ShowMasterItems="true" PageCount="1" BindingLocation="0" AllowPageShuffle="true" ItemTransform="1 0 0 1 0 0" FlattenerOverride="Default">
		<FlattenerPreference LineArtAndTextResolution="300" GradientAndMeshResolution="150" ClipComplexRegions="false" ConvertAllStrokesToOutlines="false" ConvertAllTextToOutlines="false">
			<Properties>
				<RasterVectorBalance type="double">50</RasterVectorBalance>
			</Properties>
		</FlattenerPreference>
		<Page Self="ucd" TabOrder="" AppliedMaster="ucf" OverrideList="u6482 n u649a n u6499 n" MasterPageTransform="1 0 0 1 0 0" Name="1" AppliedTrapPreset="TrapPreset/$ID/kDefaultTrapStyleName" GeometricBounds="31.181102361440935 0 810.708661416559 595.275590551" ItemTransform="1 0 0 1 -297.637795275 -420.944881885" AppliedAlternateLayout="uce" LayoutRule="UseMaster" SnapshotBlendingMode="IgnoreLayoutSnapshots" OptionalPage="false" GridStartingPoint="TopOutside" UseMasterGrid="true">
			<Properties>
				<PageColor type="enumeration">UseMasterColor</PageColor>
				<Descriptor type="list">
					<ListItem type="string"></ListItem>
					<ListItem type="enumeration">Arabic</ListItem>
					<ListItem type="boolean">true</ListItem>
					<ListItem type="boolean">false</ListItem>
					<ListItem type="long">1</ListItem>
					<ListItem type="string"></ListItem>
				</Descriptor>
			</Properties>
			<MarginPreference ColumnCount="12" ColumnGutter="14.173228346456694" Top="56.69291338582678" Bottom="56.69291338582678" Left="42.51968503937008" Right="42.51968503937008" ColumnDirection="Horizontal" ColumnsPositions="0 29.52755905501968 43.700787401476376 73.22834645649606 87.40157480295275 116.92913385797243 131.1023622044291 160.6299212594488 174.80314960590547 204.33070866092515 218.50393700738184 248.03149606240152 262.2047244088582 291.73228346387793 305.90551181033464 335.43307086535435 349.60629921181106 379.13385826683077 393.3070866132875 422.8346456683072 437.0078740147639 466.5354330697836 480.7086614162403 510.23622047126" />
			<GridDataInformation FontStyle="Regular" PointSize="12" CharacterAki="0" LineAki="9" HorizontalScale="100" VerticalScale="100" LineAlignment="LeftOrTopLineJustify" GridAlignment="AlignEmCenter" CharacterAlignment="AlignEmCenter">
				<Properties>
					<AppliedFont type="string">Adobe Arabic</AppliedFont>
				</Properties>
			</GridDataInformation>
		</Page>
		<Rectangle Self="u164" ContentType="GraphicType" StoryTitle="$ID/" OverriddenPageItemProps="" Visible="true" Name="$ID/" HorizontalLayoutConstraints="FlexibleDimension FixedDimension FlexibleDimension" VerticalLayoutConstraints="FlexibleDimension FixedDimension FlexibleDimension" GradientFillStart="0 0" GradientFillLength="0" GradientFillAngle="0" GradientStrokeStart="0 0" GradientStrokeLength="0" GradientStrokeAngle="0" ItemLayer="uc5" Locked="false" LocalDisplaySetting="Default" GradientFillHiliteLength="0" GradientFillHiliteAngle="0" GradientStrokeHiliteLength="0" GradientStrokeHiliteAngle="0" AppliedObjectStyle="ObjectStyle/$ID/[None]" ItemTransform="1 0 0 1 663.8103351363318 875.2964614390568" ParentInterfaceChangeCount="" TargetInterfaceChangeCount="" LastUpdatedInterfaceChangeCount="">
			<Properties>
				<PathGeometry>
					<GeometryPathType PathOpen="false">
						<PathPointArray>
							<PathPointType Anchor="-961.4481304113319 -1265.0602409626158" LeftDirection="-961.4481304113319 -1265.0602409626158" RightDirection="-961.4481304113319 -1265.0602409626158" />
							<PathPointType Anchor="-961.4481304113319 -485.53268190749753" LeftDirection="-961.4481304113319 -485.53268190749753" RightDirection="-961.4481304113319 -485.53268190749753" />
							<PathPointType Anchor="-366.172539861332 -485.53268190749753" LeftDirection="-366.172539861332 -485.53268190749753" RightDirection="-366.172539861332 -485.53268190749753" />
							<PathPointType Anchor="-366.172539861332 -1265.0602409626158" LeftDirection="-366.172539861332 -1265.0602409626158" RightDirection="-366.172539861332 -1265.0602409626158" />
						</PathPointArray>
					</GeometryPathType>
				</PathGeometry>
			</Properties>
			<FrameFittingOption BottomCrop="11.89868744855994" FittingOnEmptyFrame="Proportionally" />
			<ObjectExportOption AltTextSourceType="SourceXMLStructure" ActualTextSourceType="SourceXMLStructure" CustomAltText="$ID/" CustomActualText="$ID/" ApplyTagType="TagFromStructure" ImageConversionType="JPEG" ImageExportResolution="Ppi300" GIFOptionsPalette="AdaptivePalette" GIFOptionsInterlaced="true" JPEGOptionsQuality="High" JPEGOptionsFormat="BaselineEncoding" ImageAlignment="AlignLeft" ImageSpaceBefore="0" ImageSpaceAfter="0" UseImagePageBreak="false" ImagePageBreak="PageBreakBefore" CustomImageAlignment="false" SpaceUnit="CssPixel" CustomLayout="false" CustomLayoutType="AlignmentAndSpacing" EpubType="$ID/" SizeType="DefaultSize" CustomSize="$ID/" PreserveAppearanceFromLayout="PreserveAppearanceDefault">
				<Properties>
					<AltMetadataProperty NamespacePrefix="$ID/" PropertyPath="$ID/" />
					<ActualMetadataProperty NamespacePrefix="$ID/" PropertyPath="$ID/" />
				</Properties>
			</ObjectExportOption>
			<TextWrapPreference Inverse="false" ApplyToMasterPageOnly="false" TextWrapSide="BothSides" TextWrapMode="None">
				<Properties>
					<TextWrapOffset Top="0" Left="0" Bottom="0" Right="0" />
				</Properties>
				<ContourOption ContourType="SameAsClipping" IncludeInsideEdges="false" ContourPathName="$ID/" />
			</TextWrapPreference>
			<InCopyExportOption IncludeGraphicProxies="true" IncludeAllResources="false" />
			<PDF Self="u15f" GrayVectorPolicy="IgnoreAll" RGBVectorPolicy="HonorAllProfiles" CMYKVectorPolicy="HonorAllProfiles" OverriddenPageItemProps="" LocalDisplaySetting="Default" ImageTypeName="$ID/Adobe Portable Document Format (PDF)" AppliedObjectStyle="ObjectStyle/$ID/[None]" ItemTransform="0.3133021774968426 0 0 0.31330217749684264 -961.4481304113319 -1265.0602409626158" Visible="true" Name="$ID/" HorizontalLayoutConstraints="FlexibleDimension FixedDimension FlexibleDimension" VerticalLayoutConstraints="FlexibleDimension FixedDimension FlexibleDimension" ParentInterfaceChangeCount="" TargetInterfaceChangeCount="" LastUpdatedInterfaceChangeCount="">
				<Properties>
					<GraphicBounds Left="0" Top="0" Right="1900.004638671875" Bottom="2500" />
				</Properties>
				<ClippingPathSettings ClippingType="None" InvertPath="false" IncludeInsideEdges="false" RestrictToFrame="false" UseHighResolutionImage="true" Threshold="25" Tolerance="2" InsetFrame="0" AppliedPathName="$ID/" Index="-1" />
				<GraphicLayerOption UpdateLinkOption="KeepOverrides" />
				<TextWrapPreference Inverse="false" ApplyToMasterPageOnly="false" TextWrapSide="BothSides" TextWrapMode="None">
					<Properties>
						<TextWrapOffset Top="0" Left="0" Bottom="0" Right="0" />
					</Properties>
					<ContourOption ContourType="SameAsClipping" IncludeInsideEdges="false" ContourPathName="$ID/" />
				</TextWrapPreference>
				<Link Self="u163" AssetURL="$ID/" AssetID="$ID/" LinkResourceURI="file:/Users/tahiriqbal/Documents/Work/CNCF/01%20Annual%20Report%20/CNCF%20AR_01%20Folder/Links/Group%2012608.pdf" LinkResourceFormat="$ID/Adobe Portable Document Format (PDF)" StoredState="Normal" LinkClassID="35906" LinkClientID="257" LinkResourceModified="false" LinkObjectModified="false" ShowInUI="true" CanEmbed="true" CanUnembed="true" CanPackage="true" ImportPolicy="NoAutoImport" ExportPolicy="NoAutoExport" LinkImportStamp="file 132846444895465568 527080" LinkImportModificationTime="2021-12-22T12:01:29" LinkImportTime="2021-12-22T12:01:40" LinkResourceSize="0~80ae8" RenditionData="Actual" />
				<MetadataPacketPreference>
					<Properties>
						<Contents><![CDATA[<?xpacket begin="﻿" id="W5M0MpCehiHzreSzNTczkc9d"?>
<x:xmpmeta xmlns:x="adobe:ns:meta/" x:xmptk="Adobe XMP Core 6.0-c006 120.7d0d897, 2021/06/30-14:05:38        ">
   <rdf:RDF xmlns:rdf="http://www.w3.org/1999/02/22-rdf-syntax-ns#">
      <rdf:Description rdf:about=""/>
   </rdf:RDF>
</x:xmpmeta>
<?xpacket end="r"?>]]></Contents>
					</Properties>
				</MetadataPacketPreference>
				<PDFAttribute PageNumber="1" PDFCrop="CropMedia" TransparentBackground="true" />
			</PDF>
		</Rectangle>
		<Rectangle Self="u16c" ContentType="GraphicType" StoryTitle="$ID/" OverriddenPageItemProps="" Visible="true" Name="$ID/" HorizontalLayoutConstraints="FlexibleDimension FixedDimension FlexibleDimension" VerticalLayoutConstraints="FlexibleDimension FixedDimension FlexibleDimension" GradientFillStart="0 0" GradientFillLength="0" GradientFillAngle="0" GradientStrokeStart="0 0" GradientStrokeLength="0" GradientStrokeAngle="0" ItemLayer="uc5" Locked="false" LocalDisplaySetting="Default" GradientFillHiliteLength="0" GradientFillHiliteAngle="0" GradientStrokeHiliteLength="0" GradientStrokeHiliteAngle="0" AppliedObjectStyle="ObjectStyle/$ID/[None]" ItemTransform="1 0 0 1 652.3622047250001 860.236220476441" ParentInterfaceChangeCount="" TargetInterfaceChangeCount="" LastUpdatedInterfaceChangeCount="">
			<Properties>
				<PathGeometry>
					<GeometryPathType PathOpen="false">
						<PathPointArray>
							<PathPointType Anchor="-950 -1250" LeftDirection="-950 -1250" RightDirection="-950 -1250" />
							<PathPointType Anchor="-950 -466.742644011842" LeftDirection="-950 -466.742644011842" RightDirection="-950 -466.742644011842" />
							<PathPointType Anchor="-354.72440944899995 -466.742644011842" LeftDirection="-354.72440944899995 -466.742644011842" RightDirection="-354.72440944899995 -466.742644011842" />
							<PathPointType Anchor="-354.72440944899995 -1250" LeftDirection="-354.72440944899995 -1250" RightDirection="-354.72440944899995 -1250" />
						</PathPointArray>
					</GeometryPathType>
				</PathGeometry>
			</Properties>
			<FrameFittingOption FittingOnEmptyFrame="ContentToFrame" />
			<ObjectExportOption AltTextSourceType="SourceXMLStructure" ActualTextSourceType="SourceXMLStructure" CustomAltText="$ID/" CustomActualText="$ID/" ApplyTagType="TagFromStructure" ImageConversionType="JPEG" ImageExportResolution="Ppi300" GIFOptionsPalette="AdaptivePalette" GIFOptionsInterlaced="true" JPEGOptionsQuality="High" JPEGOptionsFormat="BaselineEncoding" ImageAlignment="AlignLeft" ImageSpaceBefore="0" ImageSpaceAfter="0" UseImagePageBreak="false" ImagePageBreak="PageBreakBefore" CustomImageAlignment="false" SpaceUnit="CssPixel" CustomLayout="false" CustomLayoutType="AlignmentAndSpacing" EpubType="$ID/" SizeType="DefaultSize" CustomSize="$ID/" PreserveAppearanceFromLayout="PreserveAppearanceDefault">
				<Properties>
					<AltMetadataProperty NamespacePrefix="$ID/" PropertyPath="$ID/" />
					<ActualMetadataProperty NamespacePrefix="$ID/" PropertyPath="$ID/" />
				</Properties>
			</ObjectExportOption>
			<TextWrapPreference Inverse="false" ApplyToMasterPageOnly="false" TextWrapSide="BothSides" TextWrapMode="None">
				<Properties>
					<TextWrapOffset Top="0" Left="0" Bottom="0" Right="0" />
				</Properties>
				<ContourOption ContourType="SameAsClipping" IncludeInsideEdges="false" ContourPathName="$ID/" />
			</TextWrapPreference>
			<InCopyExportOption IncludeGraphicProxies="true" IncludeAllResources="false" />
			<TransparencySetting>
				<BlendingSetting BlendMode="SoftLight" Opacity="76" />
			</TransparencySetting>
			<Image Self="u5bf" Space="$ID/#Links_RGB" ActualPpi="288 288" EffectivePpi="697 221" ImageRenderingIntent="UseColorSettings" OverriddenPageItemProps="" LocalDisplaySetting="Default" ImageTypeName="$ID/JPEG" AppliedObjectStyle="ObjectStyle/$ID/[None]" ItemTransform="0.41338582677152785 0 0 1.3048852244700675 -950.0000000000001 -1250" Visible="true" Name="$ID/" HorizontalLayoutConstraints="FlexibleDimension FixedDimension FlexibleDimension" VerticalLayoutConstraints="FlexibleDimension FixedDimension FlexibleDimension" GradientFillStart="0 0" GradientFillLength="0" GradientFillAngle="0" GradientFillHiliteLength="0" GradientFillHiliteAngle="0" ParentInterfaceChangeCount="" TargetInterfaceChangeCount="" LastUpdatedInterfaceChangeCount="">
				<Properties>
					<Profile type="string">$ID/None</Profile>
					<GraphicBounds Left="0" Top="0" Right="1440" Bottom="600.25" />
				</Properties>
				<ClippingPathSettings ClippingType="None" InvertPath="false" IncludeInsideEdges="false" RestrictToFrame="false" UseHighResolutionImage="true" Threshold="25" Tolerance="2" InsetFrame="0" AppliedPathName="$ID/" Index="-1" />
				<ImageIOPreference ApplyPhotoshopClippingPath="true" AllowAutoEmbedding="true" AlphaChannelName="$ID/" />
				<TextWrapPreference Inverse="false" ApplyToMasterPageOnly="false" TextWrapSide="BothSides" TextWrapMode="None">
					<Properties>
						<TextWrapOffset Top="0" Left="0" Bottom="0" Right="0" />
					</Properties>
					<ContourOption ContourType="SameAsClipping" IncludeInsideEdges="false" ContourPathName="$ID/" />
				</TextWrapPreference>
				<Link Self="u169" AssetURL="$ID/" AssetID="$ID/" LinkResourceURI="file:/Users/tahiriqbal/Documents/Work/CNCF/01%20Annual%20Report%20/CNCF%20AR_01%20Folder/Links/Rectangle%2016680.jpg" LinkResourceFormat="$ID/JPEG" StoredState="Normal" LinkClassID="35906" LinkClientID="257" LinkResourceModified="false" LinkObjectModified="false" ShowInUI="true" CanEmbed="true" CanUnembed="true" CanPackage="true" ImportPolicy="NoAutoImport" ExportPolicy="NoAutoExport" LinkImportStamp="file 132846485739274592 2899049" LinkImportModificationTime="2021-12-22T13:09:33" LinkImportTime="2021-12-23T08:31:15" LinkResourceSize="0~2c3c69" RenditionData="Actual" />
			</Image>
		</Rectangle>
		<Polygon Self="ue4" ContentType="Unassigned" StoryTitle="$ID/" OverriddenPageItemProps="" Visible="true" Name="$ID/" HorizontalLayoutConstraints="FlexibleDimension FixedDimension FlexibleDimension" VerticalLayoutConstraints="FlexibleDimension FixedDimension FlexibleDimension" FillColor="Color/Egg Green" StrokeWeight="1" MiterLimit="10" GradientFillStart="0 0" GradientFillLength="0" GradientFillAngle="0" GradientStrokeStart="0 0" GradientStrokeLength="0" GradientStrokeAngle="0" ItemLayer="uc5" Locked="false" LocalDisplaySetting="Default" GradientFillHiliteLength="0" GradientFillHiliteAngle="0" GradientStrokeHiliteLength="0" GradientStrokeHiliteAngle="0" AppliedObjectStyle="ObjectStyle/$ID/[None]" ItemTransform="1 0 0 1 -298.5435563302992 -933.0223235154107" ParentInterfaceChangeCount="" TargetInterfaceChangeCount="" LastUpdatedInterfaceChangeCount="">
			<Properties>
				<PathGeometry>
					<GeometryPathType PathOpen="false">
						<PathPointArray>
							<PathPointType Anchor="109.86513854218134 637.4749702584592" LeftDirection="86.97192394763944 628.4660665685415" RightDirection="132.78636982464033 646.4767128158096" />
							<PathPointType Anchor="132.62086809419782 684.0548056924086" LeftDirection="145.63693518887234 663.700131781556" RightDirection="119.60427883360694 704.4089823023884" />
							<PathPointType Anchor="67.57562962991769 704.6070572399943" LeftDirection="90.4820848601959 713.6098441291776" RightDirection="44.669224129726786 695.604270350811" />
							<PathPointType Anchor="49.66594789233418 651.4438036626636" LeftDirection="36.64004667290154 671.804097073378" RightDirection="62.692054248376806 631.0840572829094" />
						</PathPointArray>
					</GeometryPathType>
				</PathGeometry>
			</Properties>
			<ObjectExportOption AltTextSourceType="SourceXMLStructure" ActualTextSourceType="SourceXMLStructure" CustomAltText="$ID/" CustomActualText="$ID/" ApplyTagType="TagFromStructure" ImageConversionType="JPEG" ImageExportResolution="Ppi300" GIFOptionsPalette="AdaptivePalette" GIFOptionsInterlaced="true" JPEGOptionsQuality="High" JPEGOptionsFormat="BaselineEncoding" ImageAlignment="AlignLeft" ImageSpaceBefore="0" ImageSpaceAfter="0" UseImagePageBreak="false" ImagePageBreak="PageBreakBefore" CustomImageAlignment="false" SpaceUnit="CssPixel" CustomLayout="false" CustomLayoutType="AlignmentAndSpacing" EpubType="$ID/" SizeType="DefaultSize" CustomSize="$ID/" PreserveAppearanceFromLayout="PreserveAppearanceDefault">
				<Properties>
					<AltMetadataProperty NamespacePrefix="$ID/" PropertyPath="$ID/" />
					<ActualMetadataProperty NamespacePrefix="$ID/" PropertyPath="$ID/" />
				</Properties>
			</ObjectExportOption>
			<TextWrapPreference Inverse="false" ApplyToMasterPageOnly="false" TextWrapSide="BothSides" TextWrapMode="None">
				<Properties>
					<TextWrapOffset Top="0" Left="0" Bottom="0" Right="0" />
				</Properties>
			</TextWrapPreference>
			<InCopyExportOption IncludeGraphicProxies="true" IncludeAllResources="false" />
		</Polygon>
		<Polygon Self="ue6" ContentType="Unassigned" StoryTitle="$ID/" OverriddenPageItemProps="" Visible="true" Name="$ID/" HorizontalLayoutConstraints="FlexibleDimension FixedDimension FlexibleDimension" VerticalLayoutConstraints="FlexibleDimension FixedDimension FlexibleDimension" FillColor="Color/Egg Green" StrokeWeight="1" MiterLimit="10" GradientFillStart="0 0" GradientFillLength="0" GradientFillAngle="0" GradientStrokeStart="0 0" GradientStrokeLength="0" GradientStrokeAngle="0" ItemLayer="uc5" Locked="false" LocalDisplaySetting="Default" GradientFillHiliteLength="0" GradientFillHiliteAngle="0" GradientStrokeHiliteLength="0" GradientStrokeHiliteAngle="0" AppliedObjectStyle="ObjectStyle/$ID/[None]" ItemTransform="1 0 0 1 -855.4725513368277 -2098.503804671677" ParentInterfaceChangeCount="" TargetInterfaceChangeCount="" LastUpdatedInterfaceChangeCount="">
			<Properties>
				<PathGeometry>
					<GeometryPathType PathOpen="false">
						<PathPointArray>
							<PathPointType Anchor="323.61749267578125 1877.73896484375" LeftDirection="256.1835021972656 1851.20244140625" RightDirection="391.1340087890625 1904.25439453125" />
							<PathPointType Anchor="390.64650878906247 2014.9439941406251" LeftDirection="428.9864868164062 1954.9875" RightDirection="352.30499267578125 2074.8990234374996" />
							<PathPointType Anchor="199.04999999999998 2075.482470703125" LeftDirection="266.5229919433594 2102.0009765625" RightDirection="131.57715454101563 2048.9639648437496" />
							<PathPointType Anchor="146.29544677734376 1918.8854003906251" LeftDirection="107.92650146484375 1978.858447265625" RightDirection="184.6649963378906 1858.9139648437501" />
						</PathPointArray>
					</GeometryPathType>
				</PathGeometry>
			</Properties>
			<ObjectExportOption AltTextSourceType="SourceXMLStructure" ActualTextSourceType="SourceXMLStructure" CustomAltText="$ID/" CustomActualText="$ID/" ApplyTagType="TagFromStructure" ImageConversionType="JPEG" ImageExportResolution="Ppi300" GIFOptionsPalette="AdaptivePalette" GIFOptionsInterlaced="true" JPEGOptionsQuality="High" JPEGOptionsFormat="BaselineEncoding" ImageAlignment="AlignLeft" ImageSpaceBefore="0" ImageSpaceAfter="0" UseImagePageBreak="false" ImagePageBreak="PageBreakBefore" CustomImageAlignment="false" SpaceUnit="CssPixel" CustomLayout="false" CustomLayoutType="AlignmentAndSpacing" EpubType="$ID/" SizeType="DefaultSize" CustomSize="$ID/" PreserveAppearanceFromLayout="PreserveAppearanceDefault">
				<Properties>
					<AltMetadataProperty NamespacePrefix="$ID/" PropertyPath="$ID/" />
					<ActualMetadataProperty NamespacePrefix="$ID/" PropertyPath="$ID/" />
				</Properties>
			</ObjectExportOption>
			<TextWrapPreference Inverse="false" ApplyToMasterPageOnly="false" TextWrapSide="BothSides" TextWrapMode="None">
				<Properties>
					<TextWrapOffset Top="0" Left="0" Bottom="0" Right="0" />
				</Properties>
			</TextWrapPreference>
			<InCopyExportOption IncludeGraphicProxies="true" IncludeAllResources="false" />
		</Polygon>
		<TextFrame Self="u110" ParentStory="ufe" PreviousTextFrame="n" NextTextFrame="n" ContentType="TextType" OverriddenPageItemProps="" Visible="true" Name="$ID/" HorizontalLayoutConstraints="FlexibleDimension FixedDimension FlexibleDimension" VerticalLayoutConstraints="FlexibleDimension FixedDimension FlexibleDimension" GradientFillStart="0 0" GradientFillLength="0" GradientFillAngle="0" GradientStrokeStart="0 0" GradientStrokeLength="0" GradientStrokeAngle="0" ItemLayer="uc5" Locked="false" LocalDisplaySetting="Default" GradientFillHiliteLength="0" GradientFillHiliteAngle="0" GradientStrokeHiliteLength="0" GradientStrokeHiliteAngle="0" AppliedObjectStyle="ObjectStyle/$ID/[Normal Text Frame]" ItemTransform="1 0 0 1 24.58434236398763 -226.37077812933072" ParentInterfaceChangeCount="" TargetInterfaceChangeCount="" LastUpdatedInterfaceChangeCount="">
			<Properties>
				<PathGeometry>
					<GeometryPathType PathOpen="false">
						<PathPointArray>
							<PathPointType Anchor="-270.3481218909562 -37.99487118476047" LeftDirection="-270.3481218909562 -37.99487118476047" RightDirection="-270.3481218909562 -37.99487118476047" />
							<PathPointType Anchor="-270.3481218909562 -12.664957061586815" LeftDirection="-270.3481218909562 -12.664957061586815" RightDirection="-270.3481218909562 -12.664957061586815" />
							<PathPointType Anchor="-61.91662582849557 -12.664957061586815" LeftDirection="-61.91662582849557 -12.664957061586815" RightDirection="-61.91662582849557 -12.664957061586815" />
							<PathPointType Anchor="-61.91662582849557 -37.99487118476047" LeftDirection="-61.91662582849557 -37.99487118476047" RightDirection="-61.91662582849557 -37.99487118476047" />
						</PathPointArray>
					</GeometryPathType>
				</PathGeometry>
			</Properties>
			<ObjectExportOption AltTextSourceType="SourceXMLStructure" ActualTextSourceType="SourceXMLStructure" CustomAltText="$ID/" CustomActualText="$ID/" ApplyTagType="TagFromStructure" ImageConversionType="JPEG" ImageExportResolution="Ppi300" GIFOptionsPalette="AdaptivePalette" GIFOptionsInterlaced="true" JPEGOptionsQuality="High" JPEGOptionsFormat="BaselineEncoding" ImageAlignment="AlignLeft" ImageSpaceBefore="0" ImageSpaceAfter="0" UseImagePageBreak="false" ImagePageBreak="PageBreakBefore" CustomImageAlignment="false" SpaceUnit="CssPixel" CustomLayout="false" CustomLayoutType="AlignmentAndSpacing" EpubType="$ID/" SizeType="DefaultSize" CustomSize="$ID/" PreserveAppearanceFromLayout="PreserveAppearanceDefault">
				<Properties>
					<AltMetadataProperty NamespacePrefix="$ID/" PropertyPath="$ID/" />
					<ActualMetadataProperty NamespacePrefix="$ID/" PropertyPath="$ID/" />
				</Properties>
			</ObjectExportOption>
			<TextFramePreference TextColumnCount="1" TextColumnGutter="24.745377643408112" TextColumnFixedWidth="208.4314960624606" TextColumnMaxWidth="0">
				<Properties>
					<InsetSpacing type="list">
						<ListItem type="unit">0</ListItem>
						<ListItem type="unit">0</ListItem>
						<ListItem type="unit">0</ListItem>
						<ListItem type="unit">0</ListItem>
					</InsetSpacing>
				</Properties>
			</TextFramePreference>
			<TextWrapPreference Inverse="false" ApplyToMasterPageOnly="false" TextWrapSide="BothSides" TextWrapMode="None">
				<Properties>
					<TextWrapOffset Top="0" Left="0" Bottom="0" Right="0" />
				</Properties>
			</TextWrapPreference>
		</TextFrame>
		<TextFrame Self="u122" ParentStory="u126" PreviousTextFrame="n" NextTextFrame="n" ContentType="TextType" OverriddenPageItemProps="" Visible="true" Name="$ID/" HorizontalLayoutConstraints="FlexibleDimension FixedDimension FlexibleDimension" VerticalLayoutConstraints="FlexibleDimension FixedDimension FlexibleDimension" GradientFillStart="0 0" GradientFillLength="0" GradientFillAngle="0" GradientStrokeStart="0 0" GradientStrokeLength="0" GradientStrokeAngle="0" ItemLayer="uc5" Locked="false" LocalDisplaySetting="Default" GradientFillHiliteLength="0" GradientFillHiliteAngle="0" GradientStrokeHiliteLength="0" GradientStrokeHiliteAngle="0" AppliedObjectStyle="ObjectStyle/$ID/[Normal Text Frame]" ItemTransform="0.9999999999999999 0 0 0.9999999999999999 366.0701310035442 -95.53251446314972" ParentInterfaceChangeCount="" TargetInterfaceChangeCount="" LastUpdatedInterfaceChangeCount="">
			<Properties>
				<PathGeometry>
					<GeometryPathType PathOpen="false">
						<PathPointArray>
							<PathPointType Anchor="-621.1882412391741 -87.30213120137782" LeftDirection="-621.1882412391741 -87.30213120137782" RightDirection="-621.1882412391741 -87.30213120137782" />
							<PathPointType Anchor="-621.1882412391741 26.1715774149858" LeftDirection="-621.1882412391741 26.1715774149858" RightDirection="-621.1882412391741 26.1715774149858" />
							<PathPointType Anchor="-329.28123719051825 26.1715774149858" LeftDirection="-329.28123719051825 26.1715774149858" RightDirection="-329.28123719051825 26.1715774149858" />
							<PathPointType Anchor="-329.28123719051825 -87.30213120137782" LeftDirection="-329.28123719051825 -87.30213120137782" RightDirection="-329.28123719051825 -87.30213120137782" />
						</PathPointArray>
					</GeometryPathType>
				</PathGeometry>
			</Properties>
			<ObjectExportOption AltTextSourceType="SourceXMLStructure" ActualTextSourceType="SourceXMLStructure" CustomAltText="$ID/" CustomActualText="$ID/" ApplyTagType="TagFromStructure" ImageConversionType="JPEG" ImageExportResolution="Ppi300" GIFOptionsPalette="AdaptivePalette" GIFOptionsInterlaced="true" JPEGOptionsQuality="High" JPEGOptionsFormat="BaselineEncoding" ImageAlignment="AlignLeft" ImageSpaceBefore="0" ImageSpaceAfter="0" UseImagePageBreak="false" ImagePageBreak="PageBreakBefore" CustomImageAlignment="false" SpaceUnit="CssPixel" CustomLayout="false" CustomLayoutType="AlignmentAndSpacing" EpubType="$ID/" SizeType="DefaultSize" CustomSize="$ID/" PreserveAppearanceFromLayout="PreserveAppearanceDefault">
				<Properties>
					<AltMetadataProperty NamespacePrefix="$ID/" PropertyPath="$ID/" />
					<ActualMetadataProperty NamespacePrefix="$ID/" PropertyPath="$ID/" />
				</Properties>
			</ObjectExportOption>
			<TextFramePreference TextColumnCount="1" TextColumnGutter="56.858311090128126" TextColumnFixedWidth="291.90700404865584" TextColumnMaxWidth="0">
				<Properties>
					<InsetSpacing type="list">
						<ListItem type="unit">0</ListItem>
						<ListItem type="unit">0</ListItem>
						<ListItem type="unit">0</ListItem>
						<ListItem type="unit">0</ListItem>
					</InsetSpacing>
				</Properties>
			</TextFramePreference>
			<TextWrapPreference Inverse="false" ApplyToMasterPageOnly="false" TextWrapSide="BothSides" TextWrapMode="None">
				<Properties>
					<TextWrapOffset Top="0" Left="0" Bottom="0" Right="0" />
				</Properties>
			</TextWrapPreference>
		</TextFrame>
		<TextFrame Self="u143" ParentStory="u146" PreviousTextFrame="n" NextTextFrame="n" ContentType="TextType" OverriddenPageItemProps="" Visible="true" Name="$ID/" HorizontalLayoutConstraints="FlexibleDimension FixedDimension FlexibleDimension" VerticalLayoutConstraints="FlexibleDimension FixedDimension FlexibleDimension" GradientFillStart="0 0" GradientFillLength="0" GradientFillAngle="0" GradientStrokeStart="0 0" GradientStrokeLength="0" GradientStrokeAngle="0" ItemLayer="uc5" Locked="false" LocalDisplaySetting="Default" GradientFillHiliteLength="0" GradientFillHiliteAngle="0" GradientStrokeHiliteLength="0" GradientStrokeHiliteAngle="0" AppliedObjectStyle="ObjectStyle/$ID/[Normal Text Frame]" ItemTransform="0.9999999999999999 0 0 0.9999999999999999 366.0701310035441 98.07378474468487" ParentInterfaceChangeCount="" TargetInterfaceChangeCount="" LastUpdatedInterfaceChangeCount="">
			<Properties>
				<PathGeometry>
					<GeometryPathType PathOpen="false">
						<PathPointArray>
							<PathPointType Anchor="-621.1882412391741 -87.30213120137782" LeftDirection="-621.1882412391741 -87.30213120137782" RightDirection="-621.1882412391741 -87.30213120137782" />
							<PathPointType Anchor="-621.1882412391741 94.36006862090447" LeftDirection="-621.1882412391741 94.36006862090447" RightDirection="-621.1882412391741 94.36006862090447" />
							<PathPointType Anchor="-261.1146043245637 94.36006862090447" LeftDirection="-261.1146043245637 94.36006862090447" RightDirection="-261.1146043245637 94.36006862090447" />
							<PathPointType Anchor="-261.1146043245637 -87.30213120137782" LeftDirection="-261.1146043245637 -87.30213120137782" RightDirection="-261.1146043245637 -87.30213120137782" />
						</PathPointArray>
					</GeometryPathType>
				</PathGeometry>
			</Properties>
			<ObjectExportOption AltTextSourceType="SourceXMLStructure" ActualTextSourceType="SourceXMLStructure" CustomAltText="$ID/" CustomActualText="$ID/" ApplyTagType="TagFromStructure" ImageConversionType="JPEG" ImageExportResolution="Ppi300" GIFOptionsPalette="AdaptivePalette" GIFOptionsInterlaced="true" JPEGOptionsQuality="High" JPEGOptionsFormat="BaselineEncoding" ImageAlignment="AlignLeft" ImageSpaceBefore="0" ImageSpaceAfter="0" UseImagePageBreak="false" ImagePageBreak="PageBreakBefore" CustomImageAlignment="false" SpaceUnit="CssPixel" CustomLayout="false" CustomLayoutType="AlignmentAndSpacing" EpubType="$ID/" SizeType="DefaultSize" CustomSize="$ID/" PreserveAppearanceFromLayout="PreserveAppearanceDefault">
				<Properties>
					<AltMetadataProperty NamespacePrefix="$ID/" PropertyPath="$ID/" />
					<ActualMetadataProperty NamespacePrefix="$ID/" PropertyPath="$ID/" />
				</Properties>
			</ObjectExportOption>
			<TextFramePreference TextColumnCount="1" TextColumnGutter="56.858311090128126" TextColumnFixedWidth="360.0736369146104" TextColumnMaxWidth="0">
				<Properties>
					<InsetSpacing type="list">
						<ListItem type="unit">0</ListItem>
						<ListItem type="unit">0</ListItem>
						<ListItem type="unit">0</ListItem>
						<ListItem type="unit">0</ListItem>
					</InsetSpacing>
				</Properties>
			</TextFramePreference>
			<TextWrapPreference Inverse="false" ApplyToMasterPageOnly="false" TextWrapSide="BothSides" TextWrapMode="None">
				<Properties>
					<TextWrapOffset Top="0" Left="0" Bottom="0" Right="0" />
				</Properties>
			</TextWrapPreference>
		</TextFrame>
		<GraphicLine Self="u142" ContentType="Unassigned" LockState="None" OverriddenPageItemProps="" Visible="true" Name="$ID/" HorizontalLayoutConstraints="FlexibleDimension FixedDimension FlexibleDimension" VerticalLayoutConstraints="FlexibleDimension FixedDimension FlexibleDimension" MiterLimit="10" GradientFillStart="0 0" GradientFillLength="0" GradientFillAngle="0" GradientStrokeStart="0 0" GradientStrokeLength="0" GradientStrokeAngle="0" ItemLayer="uc5" Locked="false" LocalDisplaySetting="Default" GradientFillHiliteLength="0" GradientFillHiliteAngle="0" GradientStrokeHiliteLength="0" GradientStrokeHiliteAngle="0" AppliedObjectStyle="ObjectStyle/$ID/[Normal Graphics Frame]" ItemTransform="1 0 0 1 0 23.460629921259844" ParentInterfaceChangeCount="" TargetInterfaceChangeCount="" LastUpdatedInterfaceChangeCount="">
			<Properties>
				<PathGeometry>
					<GeometryPathType PathOpen="true">
						<PathPointArray>
							<PathPointType Anchor="-255.1181102356299 -49.60629921259843" LeftDirection="-255.1181102356299 -49.60629921259843" RightDirection="-255.1181102356299 -49.60629921259843" />
							<PathPointType Anchor="124.01574803120087 -49.60629921259843" LeftDirection="124.01574803120087 -49.60629921259843" RightDirection="124.01574803120087 -49.60629921259843" />
						</PathPointArray>
					</GeometryPathType>
				</PathGeometry>
			</Properties>
			<ObjectExportOption AltTextSourceType="SourceXMLStructure" ActualTextSourceType="SourceXMLStructure" CustomAltText="$ID/" CustomActualText="$ID/" ApplyTagType="TagFromStructure" ImageConversionType="JPEG" ImageExportResolution="Ppi300" GIFOptionsPalette="AdaptivePalette" GIFOptionsInterlaced="true" JPEGOptionsQuality="High" JPEGOptionsFormat="BaselineEncoding" ImageAlignment="AlignLeft" ImageSpaceBefore="0" ImageSpaceAfter="0" UseImagePageBreak="false" ImagePageBreak="PageBreakBefore" CustomImageAlignment="false" SpaceUnit="CssPixel" CustomLayout="false" CustomLayoutType="AlignmentAndSpacing" EpubType="$ID/" SizeType="DefaultSize" CustomSize="$ID/" PreserveAppearanceFromLayout="PreserveAppearanceDefault">
				<Properties>
					<AltMetadataProperty NamespacePrefix="$ID/" PropertyPath="$ID/" />
					<ActualMetadataProperty NamespacePrefix="$ID/" PropertyPath="$ID/" />
				</Properties>
			</ObjectExportOption>
			<TextWrapPreference Inverse="false" ApplyToMasterPageOnly="false" TextWrapSide="BothSides" TextWrapMode="None">
				<Properties>
					<TextWrapOffset Top="0" Left="0" Bottom="0" Right="0" />
				</Properties>
			</TextWrapPreference>
		</GraphicLine>
		<TextFrame Self="u16d" ParentStory="u170" PreviousTextFrame="n" NextTextFrame="n" ContentType="TextType" OverriddenPageItemProps="" Visible="true" Name="$ID/" HorizontalLayoutConstraints="FlexibleDimension FixedDimension FlexibleDimension" VerticalLayoutConstraints="FlexibleDimension FixedDimension FlexibleDimension" GradientFillStart="0 0" GradientFillLength="0" GradientFillAngle="0" GradientStrokeStart="0 0" GradientStrokeLength="0" GradientStrokeAngle="0" ItemLayer="uc5" Locked="false" LocalDisplaySetting="Default" GradientFillHiliteLength="0" GradientFillHiliteAngle="0" GradientStrokeHiliteLength="0" GradientStrokeHiliteAngle="0" AppliedObjectStyle="ObjectStyle/$ID/[Normal Text Frame]" ItemTransform="0.9999999999999999 0 0 0.9999999999999999 366.0701310035441 352.341501284118" ParentInterfaceChangeCount="" TargetInterfaceChangeCount="" LastUpdatedInterfaceChangeCount="">
			<Properties>
				<PathGeometry>
					<GeometryPathType PathOpen="false">
						<PathPointArray>
							<PathPointType Anchor="-621.1882412391741 -87.30213120137785" LeftDirection="-621.1882412391741 -87.30213120137785" RightDirection="-621.1882412391741 -87.30213120137785" />
							<PathPointType Anchor="-621.1882412391741 -51.58216049825285" LeftDirection="-621.1882412391741 -51.58216049825285" RightDirection="-621.1882412391741 -51.58216049825285" />
							<PathPointType Anchor="-373.1567451767726 -51.58216049825285" LeftDirection="-373.1567451767726 -51.58216049825285" RightDirection="-373.1567451767726 -51.58216049825285" />
							<PathPointType Anchor="-373.1567451767726 -87.30213120137785" LeftDirection="-373.1567451767726 -87.30213120137785" RightDirection="-373.1567451767726 -87.30213120137785" />
						</PathPointArray>
					</GeometryPathType>
				</PathGeometry>
			</Properties>
			<ObjectExportOption AltTextSourceType="SourceXMLStructure" ActualTextSourceType="SourceXMLStructure" CustomAltText="$ID/" CustomActualText="$ID/" ApplyTagType="TagFromStructure" ImageConversionType="JPEG" ImageExportResolution="Ppi300" GIFOptionsPalette="AdaptivePalette" GIFOptionsInterlaced="true" JPEGOptionsQuality="High" JPEGOptionsFormat="BaselineEncoding" ImageAlignment="AlignLeft" ImageSpaceBefore="0" ImageSpaceAfter="0" UseImagePageBreak="false" ImagePageBreak="PageBreakBefore" CustomImageAlignment="false" SpaceUnit="CssPixel" CustomLayout="false" CustomLayoutType="AlignmentAndSpacing" EpubType="$ID/" SizeType="DefaultSize" CustomSize="$ID/" PreserveAppearanceFromLayout="PreserveAppearanceDefault">
				<Properties>
					<AltMetadataProperty NamespacePrefix="$ID/" PropertyPath="$ID/" />
					<ActualMetadataProperty NamespacePrefix="$ID/" PropertyPath="$ID/" />
				</Properties>
			</ObjectExportOption>
			<TextFramePreference TextColumnCount="1" TextColumnGutter="56.858311090128126" TextColumnFixedWidth="248.03149606240152" TextColumnMaxWidth="0">
				<Properties>
					<InsetSpacing type="list">
						<ListItem type="unit">0</ListItem>
						<ListItem type="unit">0</ListItem>
						<ListItem type="unit">0</ListItem>
						<ListItem type="unit">0</ListItem>
					</InsetSpacing>
				</Properties>
			</TextFramePreference>
			<TextWrapPreference Inverse="false" ApplyToMasterPageOnly="false" TextWrapSide="BothSides" TextWrapMode="None">
				<Properties>
					<TextWrapOffset Top="0" Left="0" Bottom="0" Right="0" />
				</Properties>
			</TextWrapPreference>
		</TextFrame>
	</Spread>
</idPkg:Spread>
